orbslam3_python.libs/libopencv_superres-6f0fe9af.so.4.8.0
orbslam3_python.libs/libopencv_ml-26860ecf.so.4.8.0
orbslam3_python.libs/libopencv_mcc-2fe9ef31.so.4.8.0
orbslam3_python.libs/libopencv_shape-047e6df2.so.4.8.0
orbslam3_python.libs/libpango_vars-97b17891.so
orbslam3_python.libs/libopencv_hfs-32d3a95d.so.4.8.0
orbslam3_python.libs/libcrypto-bdaed0ea.so.1.1.1k
orbslam3_python.libs/libpango_tools-1f6bf78e.so
orbslam3_python.libs/libpango_glgeometry-851c3958.so
orbslam3_python.libs/libopencv_videostab-262c70d6.so.4.8.0
orbslam3_python.libs/libopencv_structured_light-67ae5e47.so.4.8.0
orbslam3_python.libs/libopencv_dnn-8c6fd9c7.so.4.8.0
orbslam3_python.libs/libpango_opengl-86e3f2be.so
orbslam3_python.libs/libopencv_intensity_transform-ca378733.so.4.8.0
orbslam3_python.libs/libGLEW-cc680dfb.so.2.0.0
orbslam3_python.libs/libopencv_text-a898620d.so.4.8.0
orbslam3_python.libs/libopencv_video-36c6540f.so.4.8.0
orbslam3_python.libs/libpango_image-3a91ddd2.so
orbslam3_python.libs/libopencv_quality-2cb08c6e.so.4.8.0
orbslam3_python.libs/libopencv_bioinspired-73436b9e.so.4.8.0
orbslam3_python.libs/libopencv_rgbd-47d73dd5.so.4.8.0
orbslam3_python.libs/libopencv_dnn_objdetect-c87572b5.so.4.8.0
orbslam3_python.libs/libopencv_face-63fd1d97.so.4.8.0
orbslam3_python.libs/libopencv_fuzzy-fdf42fba.so.4.8.0
orbslam3_python.libs/libtiff-84c53c12.so.5.3.0
orbslam3_python.libs/libpango_windowing-68ac2dfe.so
orbslam3_python.libs/libDBoW2-b725b211.so
orbslam3_python.libs/libopencv_reg-e6fb310b.so.4.8.0
orbslam3_python.libs/libpango_plot-77808755.so
orbslam3_python.libs/libpng16-748299c7.so.16.34.0
orbslam3_python.libs/libopencv_xfeatures2d-7dff2403.so.4.8.0
orbslam3_python.libs/libopencv_aruco-070ed9dd.so.4.8.0
orbslam3_python.libs/libpango_python-f0fe82d1.so
orbslam3_python.libs/libpango_geometry-aad1a975.so
orbslam3_python.libs/libopencv_core-f8e3c03c.so.4.8.0
orbslam3_python.libs/libORB_SLAM3-98c4e2f1.so
orbslam3_python-2.0.0.dist-info/top_level.txt
orbslam3_python-2.0.0.dist-info/WHEEL
orbslam3_python-2.0.0.dist-info/RECORD
orbslam3_python-2.0.0.dist-info/METADATA
orbslam3_python-2.0.0.dist-info/licenses/LICENSE
