Metadata-Version: 2.4
Name: orbslam3-python
Version: 2.0.0
Summary: Enhanced Python bindings for ORB-SLAM3 with hardware adaptation and performance monitoring
Author-email: "Alex S." <savaalexandru562@gmail.com>
Maintainer-email: "Alex S." <savaalexandru562@gmail.com>
License: BSD 2-Clause License
Project-URL: Homepage, https://github.com/AlexandruRO45/ORB_SLAM-PythonBindings/
Project-URL: Bug Tracker, https://github.com/AlexandruRO45/ORB_SLAM-PythonBindings/issues
Project-URL: Documentation, https://github.com/AlexandruRO45/ORB_SLAM-PythonBindings/blob/main/README.md
Project-URL: Source Code, https://github.com/AlexandruRO45/ORB_SLAM-PythonBindings/
Project-URL: Changelog, https://github.com/AlexandruRO45/ORB_SLAM-PythonBindings/blob/main/CHANGELOG.md
Keywords: slam,orb-slam,visual-slam,computer-vision,robotics,odometry,localization,mapping
Classifier: Development Status :: 4 - Beta
Classifier: Intended Audience :: Developers
Classifier: Intended Audience :: Science/Research
Classifier: Intended Audience :: Education
Classifier: License :: OSI Approved :: GNU General Public License v3 (GPLv3)
Classifier: Programming Language :: C++
Classifier: Programming Language :: Python :: 3
Classifier: Programming Language :: Python :: 3 :: Only
Classifier: Programming Language :: Python :: 3.8
Classifier: Programming Language :: Python :: 3.9
Classifier: Programming Language :: Python :: 3.10
Classifier: Programming Language :: Python :: 3.11
Classifier: Programming Language :: Python :: 3.12
Classifier: Operating System :: POSIX :: Linux
Classifier: Operating System :: MacOS
Classifier: Topic :: Scientific/Engineering :: Image Recognition
Classifier: Topic :: Scientific/Engineering :: Image Processing
Classifier: Topic :: Scientific/Engineering :: Artificial Intelligence
Classifier: Topic :: Software Development :: Libraries :: Python Modules
Classifier: Topic :: Multimedia :: Video
Requires-Python: >=3.8
License-File: LICENSE
Requires-Dist: numpy>=1.21.0
Requires-Dist: opencv-python>=4.5.0
Provides-Extra: test
Requires-Dist: pytest>=6.0; extra == "test"
Requires-Dist: pytest-cov>=3.0; extra == "test"
Provides-Extra: dev
Requires-Dist: pytest>=6.0; extra == "dev"
Requires-Dist: pytest-cov>=3.0; extra == "dev"
Requires-Dist: build; extra == "dev"
Requires-Dist: twine; extra == "dev"
Requires-Dist: black>=22.0; extra == "dev"
Requires-Dist: flake8>=4.0; extra == "dev"
Requires-Dist: mypy>=0.950; extra == "dev"
Provides-Extra: docs
Requires-Dist: sphinx>=4.0; extra == "docs"
Requires-Dist: sphinx-rtd-theme>=1.0; extra == "docs"
Requires-Dist: sphinx-autodoc-typehints>=1.12; extra == "docs"
Provides-Extra: full
Requires-Dist: orbslam3-python[dev,docs,test]; extra == "full"
Dynamic: license-file
